xrosfs/__init__.py
xrosfs/__main__.py
xrosfs/args.py
xrosfs/cmdbuilder.py
xrosfs/conshell.py
xrosfs/xros_utils.py
xrosfs/xrosfs.py
xrosfs-0.1.1.dist-info/DESCRIPTION.rst
xrosfs-0.1.1.dist-info/METADATA
xrosfs-0.1.1.dist-info/RECORD
xrosfs-0.1.1.dist-info/WHEEL
xrosfs-0.1.1.dist-info/entry_points.txt
xrosfs-0.1.1.dist-info/metadata.json
xrosfs-0.1.1.dist-info/top_level.txt
