Metadata-Version: 2.0
Name: xrosfs
Version: 0.1.1
Summary: Mount a Running Docker Container File Sytem via FUSE
Home-page: https://github.com/hankei6km/xrosfs
Author: hankei6km
Author-email: hankei6km@gmail.com
License: MIT
Platform: UNKNOWN
Classifier: Development Status :: 2 - Pre-Alpha
Classifier: Topic :: System :: Filesystems
Classifier: License :: OSI Approved :: MIT License
Classifier: Operating System :: POSIX :: Linux
Classifier: Environment :: Console
Classifier: Programming Language :: Python :: 3
Classifier: Programming Language :: Python :: 3.5
Classifier: Programming Language :: Python :: 3.6
Requires-Dist: docker
Requires-Dist: fusepy
